tgfp_lib/__init__.py
tgfp_lib/config/__init__.py
tgfp_lib/config/config.py
tgfp_lib/config/prefect_helpers/__init__.py
tgfp_lib/config/prefect_helpers/helpers.py
tgfp_lib/tgfp.py
tgfp_lib-2.7.2.dist-info/METADATA
tgfp_lib-2.7.2.dist-info/WHEEL
tgfp_lib-2.7.2.dist-info/RECORD
