Metadata-Version: 2.1
Name: tgfp-lib
Version: 2.7.2
Summary: The Great Football Pool Project
License: MIT
Author: John Sturgeon
Author-email: john.sturgeon@me.com
Requires-Python: >=3.10,<4.0
Classifier: License :: OSI Approved :: MIT License
Classifier: Programming Language :: Python :: 3
Classifier: Programming Language :: Python :: 3.10
Classifier: Programming Language :: Python :: 3.11
Classifier: Programming Language :: Python :: 3.12
Requires-Dist: beanie (>=1.23.6,<2.0.0)
Requires-Dist: prefect (>=2.14.6,<3.0.0)
Requires-Dist: pylint (>=3.0.2,<4.0.0)
Requires-Dist: pymongo (>=4.6.0,<5.0.0)
Requires-Dist: pytz (>=2023.3.post1,<2024.0)
